LICENSE
README.rst
setup.py
bin/qas
qas/__init__.py
qas.egg-info/PKG-INFO
qas.egg-info/SOURCES.txt
qas.egg-info/dependency_links.txt
qas.egg-info/requires.txt
qas.egg-info/top_level.txt
qas/assertion/__init__.py
qas/assertion/expect.py
qas/assertion/expect_test.py
qas/driver/__init__.py
qas/driver/driver.py
qas/driver/elasticsearch_driver.py
qas/driver/elasticsearch_driver_test.py
qas/driver/grpc_driver.py
qas/driver/grpc_driver_test.py
qas/driver/http_driver.py
qas/driver/mns_driver.py
qas/driver/mns_driver_test.py
qas/driver/mongo_driver.py
qas/driver/mongo_driver_test.py
qas/driver/mysql_driver.py
qas/driver/mysql_driver_test.py
qas/driver/oss_driver.py
qas/driver/oss_driver_test.py
qas/driver/ots_driver.py
qas/driver/ots_driver_test.py
qas/driver/pop_driver.py
qas/driver/redis_driver.py
qas/driver/redis_driver_test.py
qas/driver/shell_driver.py
qas/driver/shell_driver_test.py
qas/driver/sls_driver.py
qas/driver/sls_driver_test.py
qas/driver/thrift_driver.py
qas/driver/thrift_driver_test.py
qas/framework/__init__.py
qas/framework/framework.py
qas/framework/framework_test.py
qas/framework/generate.py
qas/framework/generate_test.py
qas/framework/retry_until.py
qas/hook/__init__.py
qas/hook/debug_hook.py
qas/hook/dingtalk_hook.py
qas/hook/dingtalk_hook_test.py
qas/hook/email_hook.py
qas/hook/email_hook_test.py
qas/hook/hook.py
qas/hook/report_hook.py
qas/hook/slslog_hook.py
qas/hook/stdlog_hook.py
qas/i18n/__init__.py
qas/i18n/i18n.py
qas/reporter/__init__.py
qas/reporter/format_step_res.py
qas/reporter/html_reporter.py
qas/reporter/html_reporter_test.py
qas/reporter/json_reporter.py
qas/reporter/reporter.py
qas/reporter/text_reporter.py
qas/result/__init__.py
qas/result/result.py
qas/util/__init__.py
qas/util/exec_func.py
qas/util/include.py
qas/util/merge.py
qas/util/merge_test.py
qas/util/render.py
qas/util/render_test.py