Metadata-Version: 2.1
Name: qas
Version: 1.0.8
Summary: A general, concurrent and extensible functional testing framework
Home-page: https://github.com/hatlonely/qas
Author: hatlonely
Author-email: hatlonely@foxmail.com
License:                                  Apache License
Keywords: qas
Platform: UNKNOWN
License-File: LICENSE
